LICENSE
inclusive_django_range_fields/__init__.py
inclusive_django_range_fields/drf/__init__.py
inclusive_django_range_fields/drf/fields.py
inclusive_django_range_fields/fields.py
inclusive_django_range_fields/forms.py
inclusive_django_range_fields/ranges.py
inclusive_django_range_fields/settings.py
inclusive_django_range_fields-0.2.3.dist-info/LICENSE
inclusive_django_range_fields-0.2.3.dist-info/WHEEL
inclusive_django_range_fields-0.2.3.dist-info/METADATA
inclusive_django_range_fields-0.2.3.dist-info/RECORD
