Metadata-Version: 2.1
Name: inclusive-django-range-fields
Version: 0.2.3
Summary: Inclusive Django Range Fields which uses default bounds as '[]'
Home-page: https://github.com/hipo/inclusive-django-range-fields
License: Apache-2.0
Keywords: python,django,django rest framework,postgres,range field
Author: Hipo
Author-email: pypi@hipolabs.com
Requires-Python: >=2.7
Classifier: Framework :: Django
Classifier: License :: OSI Approved :: Apache Software License
Classifier: Operating System :: OS Independent
Classifier: Programming Language :: Python
Classifier: Programming Language :: Python :: 2
Classifier: Programming Language :: Python :: 2.7
Classifier: Programming Language :: Python :: 3
Classifier: Programming Language :: Python :: 3.4
Classifier: Programming Language :: Python :: 3.5
Classifier: Programming Language :: Python :: 3.6
Classifier: Programming Language :: Python :: 3.7
Classifier: Programming Language :: Python :: 3.8
Classifier: Topic :: Internet :: WWW/HTTP
Classifier: Topic :: Internet :: WWW/HTTP :: Dynamic Content
Classifier: Topic :: Software Development :: Libraries :: Python Modules
Requires-Dist: Django (>=1.8)
Requires-Dist: djangorestframework (>=3.0)
Project-URL: Repository, https://github.com/hipo/inclusive-django-range-fields
